{
  "map": [
    {
      "lat": 1.28692,
      "long": 103.85457,
      "name": "Merlion",
      "desc": "Tourist Atraction"
    },
    {
      "lat": 1.287466,
      "long": 103.851424,
      "name": "AsianCivilisationsMuseum",
      "desc": "Tourist Atraction"
    },
    {
      "lat": 1.290555,
      "long": 103.846188,
      "name": "ClarkeQuay",
      "desc": "Tourist Atraction"
    },
    {
      "lat": 1.295526,
      "long": 103.845331,
      "name": "Fort Canning Park",
      "desc": "Tourist Atraction"
    },
    {
      "lat": 1.302279,
      "long": 103.837399,
      "name": "Orchard Road",
      "desc": "Tourist Atraction"
    },
    {
      "lat": 1.289332,
      "long": 103.863152,
      "name": "Orchard Road",
      "desc": "Tourist Atraction"
    },
    {
      "lat": 1.283099,
      "long": 103.860295,
      "name": "MarinaBaySands",
      "desc": "Tourist Atraction"
    },
    {
      "lat": 1.28179,
      "long": 103.863954,
      "name": "GardensByTheBay",
      "desc": "Tourist Atraction"
    },
    {
      "lat": 1.284193,
      "long": 103.843362,
      "name": "Chinatown",
      "desc": "Tourist Atraction"
    }
  ]
}
